pieoffice/.template.py
pieoffice/__init__.py
pieoffice/__main__.py
pieoffice/armenian.py
pieoffice/avestan.py
pieoffice/carian.py
pieoffice/cypriot.py
pieoffice/gothic.py
pieoffice/greek.py
pieoffice/linearb.py
pieoffice/luwian.py
pieoffice/lycian.py
pieoffice/lydian.py
pieoffice/ogham.py
pieoffice/oldpersian.py
pieoffice/oscan.py
pieoffice/pie.py
pieoffice/tools.py
pieoffice/vedic.py
pieoffice-1.3.2.dist-info/LICENSE
pieoffice-1.3.2.dist-info/WHEEL
pieoffice-1.3.2.dist-info/METADATA
pieoffice-1.3.2.dist-info/RECORD
